README.md
fanchart/__init__.py
fanchart/_version.py
fanchart/plot.py
fanchart/data/fan_history_2019Q3.csv
fanchart/data/fan_history_2022Q1.csv
fanchart/data/fan_history_2022Q3.csv
fanchart/data/fan_parameters_2019Q3.csv
fanchart/data/fan_parameters_2022Q1.csv
fanchart/data/fan_parameters_2022Q3.csv
fanchart-1.1.0.dist-info/METADATA
fanchart-1.1.0.dist-info/WHEEL
fanchart-1.1.0.dist-info/licenses/LICENSE
fanchart-1.1.0.dist-info/RECORD
