Metadata-Version: 2.1
Name: fanchart
Version: 1.1.0
Summary: Library to create Fan Charts as introduced by the Bank of England in 1996.
Project-URL: Homepage, https://github.com/quantgirluk/fanchart
Project-URL: Bug Tracker, https://github.com/quantgirluk/fanchart/issues
Author-email: Dialid Santiago <d.santiago@outlook.com>
License-File: LICENSE
Classifier: License :: OSI Approved :: MIT License
Classifier: Operating System :: OS Independent
Classifier: Programming Language :: Python :: 3
Classifier: Topic :: Scientific/Engineering :: Mathematics
Classifier: Topic :: Scientific/Engineering :: Visualization
Requires-Python: <3.11,>=3.8
Requires-Dist: matplotlib>=3.6.2
Requires-Dist: numpy<1.24.0
Requires-Dist: pandas>=1.5.3
Requires-Dist: twopiece>=1.3.1
